esc2esc/__init__.py
esc2esc-0.0.2.dist-info/LICENSE
esc2esc-0.0.2.dist-info/METADATA
esc2esc-0.0.2.dist-info/WHEEL
esc2esc-0.0.2.dist-info/top_level.txt
esc2esc-0.0.2.dist-info/RECORD
