Metadata-Version: 2.2
Name: esc2esc
Version: 0.0.2
Summary: Press ESC to interrupt
Home-page: https://github.com/takeiteasy/esc2esc
Author: George Watson
Author-email: George Watson <gigolo@hotmail.co.uk>
Project-URL: Homepage, https://github.com/takeiteasy/esc2esc
Project-URL: Issues, https://github.com/takeiteasy/esc2esc/issues
Classifier: Programming Language :: Python :: 3
Classifier: License :: OSI Approved :: MIT License
Classifier: Operating System :: OS Independent
Requires-Python: >=3.8
License-File: LICENSE
Dynamic: author
Dynamic: home-page
